unicef_snapshot/__init__.py
unicef_snapshot/admin.py
unicef_snapshot/models.py
unicef_snapshot/serializers.py
unicef_snapshot/urls.py
unicef_snapshot/utils.py
unicef_snapshot/views.py
unicef_snapshot/migrations/0001_initial.py
unicef_snapshot/migrations/__init__.py
unicef_snapshot-1.3.dist-info/LICENSE
unicef_snapshot-1.3.dist-info/METADATA
unicef_snapshot-1.3.dist-info/WHEEL
unicef_snapshot-1.3.dist-info/top_level.txt
unicef_snapshot-1.3.dist-info/RECORD
