Metadata-Version: 2.1
Name: unicef-snapshot
Version: 1.3
Summary: Snapshot of data changes in django models
Home-page: https://github.com/unicef/unicef-snapshot
Author: UNICEF
Author-email: dev@unicef.org
License: Apache 2 License
Platform: any
Classifier: Environment :: Web Environment
Classifier: Programming Language :: Python :: 3.9
Classifier: Framework :: Django
Classifier: Framework :: Django :: 3.2
Classifier: Framework :: Django :: 4.0
Classifier: Framework :: Django :: 4.1
Classifier: Intended Audience :: Developers
License-File: LICENSE
Requires-Dist: djangorestframework
Requires-Dist: django-model-utils
Requires-Dist: Django
Requires-Dist: pytz
Provides-Extra: test
Requires-Dist: coverage ; extra == 'test'
Requires-Dist: django-fsm ; extra == 'test'
Requires-Dist: factory-boy ; extra == 'test'
Requires-Dist: faker ; extra == 'test'
Requires-Dist: flake8 ; extra == 'test'
Requires-Dist: isort ; extra == 'test'
Requires-Dist: pytest ; extra == 'test'
Requires-Dist: pytest-cov ; extra == 'test'
Requires-Dist: pytest-django ; extra == 'test'
Requires-Dist: pytest-echo ; extra == 'test'
Requires-Dist: psycopg2-binary ; extra == 'test'
